[
  {
    "title": "Dax Harwood: My Plan Is To Have A Nice Conversation With Willow Tonight!",
    "summary": "Dax Harwood previews a mixed tag team match set for tonight's edition of AEW Collision. On the October 11th edition of AEW Collision, a mixed trios match is set to take place, as Megan Bayne will...",
    "source": "Fightful",
    "url": "https://www.fightful.com/wrestling/dax-harwood-my-plan-is-to-have-a-nice-conversation-with-willow-tonight",
    "publishedAt": "2025-10-11T15:40:53+00:00",
    "category": "aew"
  },
  {
    "title": "Darby Allin Attacks Jon Moxley At New York Comic Con",
    "summary": "Darby Allin and Jon Moxley continued their feud in an unexpected place this week. During a recent panel for All Elite Wrestling at New York Comic Con, Moxley appeared. After the panel, Moxley was...",
    "source": "Wrestlezone",
    "url": "https://www.wrestlezone.com/news/1584396-darby-allin-attacks-jon-moxley-at-new-york-comic-con",
    "publishedAt": "2025-10-11T00:57:35+00:00",
    "category": "aew"
  }
]